invade/__init__.py
invade/main.py
invade/version.py
invade/winapi.py
invade-0.0.6.dist-info/METADATA
invade-0.0.6.dist-info/RECORD
invade-0.0.6.dist-info/WHEEL
invade-0.0.6.dist-info/top_level.txt
