Metadata-Version: 2.1
Name: invade
Version: 0.0.6
Summary: A library for interacting with Windows process memory
Home-page: https://github.com/cgio/invade
Author: Chad Gosselin
License: UNKNOWN
Platform: UNKNOWN
Classifier: Programming Language :: Python :: 3.6
Classifier: License :: OSI Approved :: MIT License
Classifier: Natural Language :: English
Classifier: Operating System :: Microsoft :: Windows
Classifier: Topic :: Security
Classifier: Intended Audience :: Developers
Classifier: Intended Audience :: Science/Research
Requires-Python: >=3.6
Requires-Dist: pefile
